cegalprizm/pycoderunner/__init__.py
cegalprizm/pycoderunner/__main__.py
cegalprizm/pycoderunner/constants.py
cegalprizm/pycoderunner/file_services.py
cegalprizm/pycoderunner/globals.py
cegalprizm/pycoderunner/hub_helper.py
cegalprizm/pycoderunner/notebook.py
cegalprizm/pycoderunner/prizmworkflowrunner_pb2.py
cegalprizm/pycoderunner/pycoderunner_pb2.py
cegalprizm/pycoderunner/python_code_parser.py
cegalprizm/pycoderunner/redirects.py
cegalprizm/pycoderunner/script.py
cegalprizm/pycoderunner/script_library.py
cegalprizm/pycoderunner/task_registry.py
cegalprizm/pycoderunner/value_parameters.py
cegalprizm/pycoderunner/workflow_description.py
cegalprizm/pycoderunner/workflow_inputs.py
cegalprizm/pycoderunner/workflow_library.py
cegalprizm/pycoderunner/enums/domain_objects.py
cegalprizm/pycoderunner/enums/measurement_names.py
cegalprizm/pycoderunner/enums/template_names.py
cegalprizm/pycoderunner/enums/well_known_folders.py
cegalprizm/pycoderunner/tasks/create_function.py
cegalprizm/pycoderunner/tasks/execute_function.py
cegalprizm/pycoderunner/tasks/list_workflows.py
cegalprizm/pycoderunner/tasks/run_script.py
cegalprizm/pycoderunner/tasks/run_workflow.py
cegalprizm/pycoderunner/tasks/run_workflow_mp_queue.py
cegalprizm/pycoderunner/tasks/run_workflow_process_pool.py
cegalprizm_pycoderunner-1.4.0.dist-info/LICENSE
cegalprizm_pycoderunner-1.4.0.dist-info/METADATA
cegalprizm_pycoderunner-1.4.0.dist-info/WHEEL
cegalprizm_pycoderunner-1.4.0.dist-info/top_level.txt
cegalprizm_pycoderunner-1.4.0.dist-info/RECORD
