Metadata-Version: 2.1
Name: cegalprizm-pycoderunner
Version: 1.4.0
Summary: Cegal Prizm PyCode Runner
Home-page: https://docs.prizm.cegal-geo.com/
Author: Cegal Prizm Team
Author-email: prizm@cegal.com
Classifier: Programming Language :: Python :: 3
Classifier: License :: Other/Proprietary License
Classifier: Operating System :: OS Independent
Requires-Python: >=3.6
License-File: LICENSE
Requires-Dist: grpcio
Requires-Dist: protobuf
Requires-Dist: argparse
Requires-Dist: asyncio
Requires-Dist: black
Requires-Dist: papermill
Requires-Dist: ipykernel
Requires-Dist: numpy
Requires-Dist: cloudpickle
Requires-Dist: cegalprizm-hub <2,>=1.2.4
